pygame_easy_menu/__init__.py
pygame_easy_menu/main.py
pygame_easy_menu/tools.py
pygame_easy_menu/assets/background.png
pygame_easy_menu-0.0.61.dist-info/METADATA
pygame_easy_menu-0.0.61.dist-info/WHEEL
pygame_easy_menu-0.0.61.dist-info/top_level.txt
pygame_easy_menu-0.0.61.dist-info/RECORD
