Metadata-Version: 2.1
Name: pygame-easy-menu
Version: 0.0.61
Author: Paul Mairesse
Author-email: paul.mairesse@free.fr
License: MIT
Classifier: Programming Language :: Python :: 3
Classifier: License :: OSI Approved :: MIT License
Classifier: Operating System :: OS Independent
Requires: textwrap3
Requires: pygame
Requires: pathlib
Requires: logging
